denon_avr_serial_over_ip/__init__.py
denon_avr_serial_over_ip/main.py
denon_avr_serial_over_ip/skeleton.py
denon_avr_serial_over_ip/exceptions/__init__.py
denon_avr_serial_over_ip/exceptions/exceptions.py
denon_avr_serial_over_ip/poll/__init__.py
denon_avr_serial_over_ip/poll/poll.py
denon_avr_serial_over_ip/protocol/__init__.py
denon_avr_serial_over_ip/protocol/protocol.py
denon_avr_serial_over_ip/zone/__init__.py
denon_avr_serial_over_ip/zone/zone.py
denon_avr_serial_over_ip-0.0.5.dist-info/AUTHORS.rst
denon_avr_serial_over_ip-0.0.5.dist-info/LICENSE.txt
denon_avr_serial_over_ip-0.0.5.dist-info/METADATA
denon_avr_serial_over_ip-0.0.5.dist-info/WHEEL
denon_avr_serial_over_ip-0.0.5.dist-info/top_level.txt
denon_avr_serial_over_ip-0.0.5.dist-info/RECORD
