Metadata-Version: 2.1
Name: denon-avr-serial-over-ip
Version: 0.0.5
Summary: Control a serial Denon AVR interface over IP
Home-page: https://github.com/troykelly/python-denon-avr-serial-over-ip
Author: Troy Kelly
Author-email: troy@troykelly.com
License: cc0
Project-URL: Documentation, https://github.com/troykelly/python-denon-avr-serial-over-ip/wiki
Project-URL: Issues, https://github.com/troykelly/python-denon-avr-serial-over-ip/issues
Platform: any
Classifier: Development Status :: 4 - Beta
Classifier: Programming Language :: Python
Provides-Extra: testing
Requires-Dist: pytest ; extra == 'testing'
Requires-Dist: pytest-cov ; extra == 'testing'
